{
    "profiles": [
        {
            "complex_modifications": {
                "rules": [
                    {
                        "description": "Control + Insert to Copy, Shift + Insert to Paste",
                        "manipulators": [
                            {
                                "from": {
                                    "key_code": "insert",
                                    "modifiers": {
                                        "mandatory": ["control"]
                                    }
                                },
                                "to": [
                                    {
                                        "key_code": "c",
                                        "modifiers": ["command"]
                                    }
                                ],
                                "type": "basic"
                            },
                            {
                                "from": {
                                    "key_code": "insert",
                                    "modifiers": {
                                        "mandatory": ["shift"]
                                    }
                                },
                                "to": [
                                    {
                                        "key_code": "v",
                                        "modifiers": ["command"]
                                    }
                                ],
                                "type": "basic"
                            }
                        ]
                    }
                ]
            },
            "name": "Default profile",
            "selected": true,
            "virtual_hid_keyboard": { "keyboard_type_v2": "iso" }
        }
    ]
}